nepali_stemmer/__init__.py
nepali_stemmer/helper.py
nepali_stemmer/root.py
nepali_stemmer/stemmer.py
nepali_stemmer/files/__init__.py
nepali_stemmer/files/dictionary.txt
nepali_stemmer/files/suffix.txt
stemmer/__init__.py
stemmer/nep_stemmer.py
stemmer/root.py
nepali_stemmer-0.0.2.dist-info/LICENSE
nepali_stemmer-0.0.2.dist-info/METADATA
nepali_stemmer-0.0.2.dist-info/WHEEL
nepali_stemmer-0.0.2.dist-info/top_level.txt
nepali_stemmer-0.0.2.dist-info/RECORD
