Metadata-Version: 2.1
Name: nepali-stemmer
Version: 0.0.2
Summary: A simple Nepali stemmer
Home-page: https://github.com/oya163/nepali-stemmer
Author: Oyesh Mann Singh
Author-email: osingh1@umbc.edu
License: UNKNOWN
Platform: UNKNOWN
Classifier: Programming Language :: Python :: 3
Classifier: License :: OSI Approved :: MIT License
Classifier: Operating System :: OS Independent
Requires-Python: >=3.6
